resume_copilot_lib/__init__.py
resume_copilot_lib/job_search.py
resume_copilot_lib-1.0.0.dist-info/METADATA
resume_copilot_lib-1.0.0.dist-info/WHEEL
resume_copilot_lib-1.0.0.dist-info/top_level.txt
resume_copilot_lib-1.0.0.dist-info/RECORD
