Metadata-Version: 2.2
Name: resume-copilot-lib
Version: 1.0.0
Summary: A Python library to interact with the Resume Copilot API, allowing job search integration into applications.
Home-page: https://resumecopilot.net/
Author: ResumeCopilot
Author-email: support@resumecopilot.net
Project-URL: Homepage, https://resumecopilot.net/
Project-URL: Documentation, https://api.resumecopilot.net/swagger/index.html
Project-URL: Source Code, https://github.com/resumecopilot-net/resume-copilot-lib-python
Project-URL: Bug Tracker, https://github.com/resumecopilot-net/resume-copilot-lib-python/issues
Classifier: Programming Language :: Python :: 3
Classifier: License :: OSI Approved :: MIT License
Classifier: Operating System :: OS Independent
Requires-Python: >=3.6
Requires-Dist: requests>=2.28.0
Dynamic: author
Dynamic: author-email
Dynamic: classifier
Dynamic: description
Dynamic: description-content-type
Dynamic: home-page
Dynamic: project-url
Dynamic: requires-dist
Dynamic: requires-python
Dynamic: summary
